pypkgs_pf/__init__.py
pypkgs_pf/pypkgs_pf.py
pypkgs_pf-0.1.0.dist-info/LICENSE
pypkgs_pf-0.1.0.dist-info/WHEEL
pypkgs_pf-0.1.0.dist-info/METADATA
pypkgs_pf-0.1.0.dist-info/RECORD
